MANIFEST.in
README.txt
setup.py
version.txt
ooxml/__init__.py
ooxml/ooxmlbase.py
ooxml/spreadsheet.py
ooxml.egg-info/PKG-INFO
ooxml.egg-info/SOURCES.txt
ooxml.egg-info/dependency_links.txt
ooxml.egg-info/top_level.txt