Metadata-Version: 1.0
Name: ooxml
Version: 0.2.1
Summary: Python interface for working with OOXML files such as docx, xlsx.
Home-page: https://bitbucket.org/wensheng/pyooxml
Author: Wensheng Wang
Author-email: wenshengwang@gmail.com
License: MIT
Keywords: word excel powerpoint ooxml
Platform: Platform Independent
Classifier: Operating System :: OS Independent
Classifier: Programming Language :: Python
Classifier: License :: OSI Approved :: MIT License
Classifier: Development Status :: 3 - Alpha
Classifier: Intended Audience :: Developers
Classifier: Topic :: Office/Business :: Financial :: Spreadsheet
Classifier: Topic :: Software Development :: Libraries :: Python Modules
